pacing/__init__.py
pacing/utils.py
auto_pacing-0.0.4.dist-info/LICENSE
auto_pacing-0.0.4.dist-info/METADATA
auto_pacing-0.0.4.dist-info/WHEEL
auto_pacing-0.0.4.dist-info/top_level.txt
auto_pacing-0.0.4.dist-info/RECORD
