Metadata-Version: 2.1
Name: auto-pacing
Version: 0.0.4
Summary: Utilities designed to automatically set and adjust the pace a time series based on historical trends and specific performance targets.
Home-page: https://github.com/maucoin/auto-pacing
Author: Michael Aucoin
Author-email: michael@clicktripz.com
License: UNKNOWN
Platform: UNKNOWN
Classifier: Programming Language :: Python :: 3
Classifier: License :: OSI Approved :: MIT License
Classifier: Operating System :: OS Independent
Requires-Python: >=3.6
